groupdocs/watermark/py.typed
aspose/pycore/py.typed
aspose/pycore/__init__.pyi
aspose/pyreflection/py.typed
aspose/pyreflection/__init__.pyi
aspose/pydrawing/py.typed
aspose/pydrawing/__init__.pyi
aspose/pydrawing/design.pyi
aspose/pydrawing/drawing2d.pyi
aspose/pydrawing/imaging.pyi
aspose/pydrawing/printing.pyi
aspose/pydrawing/text.pyi
groupdocs/watermark/__init__.pyi
groupdocs/watermark/common/__init__.pyi
groupdocs/watermark/contents/__init__.pyi
groupdocs/watermark/contents/diagram/__init__.pyi
groupdocs/watermark/contents/email/__init__.pyi
groupdocs/watermark/contents/image/__init__.pyi
groupdocs/watermark/contents/pdf/__init__.pyi
groupdocs/watermark/contents/presentation/__init__.pyi
groupdocs/watermark/contents/spreadsheet/__init__.pyi
groupdocs/watermark/contents/wordprocessing/__init__.pyi
groupdocs/watermark/exceptions/__init__.pyi
groupdocs/watermark/internal/__init__.pyi
groupdocs/watermark/options/__init__.pyi
groupdocs/watermark/options/diagram/__init__.pyi
groupdocs/watermark/options/email/__init__.pyi
groupdocs/watermark/options/image/__init__.pyi
groupdocs/watermark/options/pdf/__init__.pyi
groupdocs/watermark/options/presentation/__init__.pyi
groupdocs/watermark/options/spreadsheet/__init__.pyi
groupdocs/watermark/options/wordprocessing/__init__.pyi
groupdocs/watermark/search/__init__.pyi
groupdocs/watermark/search/objects/__init__.pyi
groupdocs/watermark/search/searchcriteria/__init__.pyi
groupdocs/watermark/search/watermarks/__init__.pyi
groupdocs/watermark/watermarks/__init__.pyi
groupdocs/watermark/watermarks/results/__init__.pyi
groupdocs/__init__.py
groupdocs/pycore.cp310-win32.pyd
groupdocs/pycore.cp311-win32.pyd
groupdocs/pycore.cp312-win32.pyd
groupdocs/pycore.cp313-win32.pyd
groupdocs/pycore.cp35-win32.pyd
groupdocs/pycore.cp36-win32.pyd
groupdocs/pycore.cp37-win32.pyd
groupdocs/pycore.cp38-win32.pyd
groupdocs/pycore.cp39-win32.pyd
groupdocs/pygc.cp310-win32.pyd
groupdocs/pygc.cp311-win32.pyd
groupdocs/pygc.cp312-win32.pyd
groupdocs_watermark_net-25.12.dist-info/METADATA
groupdocs_watermark_net-25.12.dist-info/WHEEL
groupdocs_watermark_net-25.12.dist-info/entry_points.txt
groupdocs_watermark_net-25.12.dist-info/top_level.txt
groupdocs_watermark_net-25.12.dist-info/RECORD
