Metadata-Version: 2.1
Name: groupdocs-watermark-net
Version: 25.12
Summary: GroupDocs.Watermark is a powerful document watermarking API that allows to add image and text watermarks. Additionally, it can search and remove the watermarks which were added to the documents by other third-party software.
Home-page: https://products.groupdocs.com/watermark
Author: GroupDocs
License: Other/Proprietary License
Keywords: watermark,digital-watermarking,text-watermark,image-watermark,pdf-watermark,pptx-docx-xlsx,png,word,excel,powerpoint,visio,image
Platform: win32
Classifier: Operating System :: Microsoft :: Windows
Classifier: Operating System :: POSIX :: Linux
Classifier: Operating System :: Unix
Classifier: License :: Other/Proprietary License
Classifier: Programming Language :: Python :: 3
Classifier: Programming Language :: Python :: 3 :: Only
Classifier: Programming Language :: Python :: 3.8
Classifier: Programming Language :: Python :: 3.9
Classifier: Topic :: Software Development :: Libraries
Classifier: Topic :: Utilities
Requires-Python: >=3.5,<3.14
